dql_parser/__init__.py
dql_parser/ast_nodes.py
dql_parser/cache.py
dql_parser/error_collector.py
dql_parser/error_messages.py
dql_parser/exceptions.py
dql_parser/expression_validator.py
dql_parser/file_resolver.py
dql_parser/fuzzy_matcher.py
dql_parser/grammar.lark
dql_parser/macro_registry.py
dql_parser/parse_result.py
dql_parser/parser.py
dql_parser/profiler.py
dql_parser/transformer.py
dql_parser/typo_dictionary.py
dql_parser-0.5.2.dist-info/licenses/LICENSE
dql_parser-0.5.2.dist-info/METADATA
dql_parser-0.5.2.dist-info/WHEEL
dql_parser-0.5.2.dist-info/top_level.txt
dql_parser-0.5.2.dist-info/RECORD
