Metadata-Version: 2.4
Name: dql-parser
Version: 0.5.2
Summary: Pure Python parser for Data Quality Language (DQL)
Author-email: "stratege.ai Team" <info@stratege.ai>
License: MIT
Project-URL: Homepage, https://stratege.ai/tools/dql-parser
Project-URL: Documentation, https://dql-parser.readthedocs.io
Project-URL: Repository, https://github.com/stratege.ai/dql-parser
Project-URL: Issues, https://github.com/stratege.ai/dql-parser/issues
Project-URL: Changelog, https://github.com/stratege.ai/dql-parser/blob/main/CHANGELOG.md
Keywords: dql,parser,data-quality,validation
Classifier: Development Status :: 3 - Alpha
Classifier: Intended Audience :: Developers
Classifier: License :: OSI Approved :: MIT License
Classifier: Programming Language :: Python :: 3
Classifier: Programming Language :: Python :: 3.8
Classifier: Programming Language :: Python :: 3.9
Classifier: Programming Language :: Python :: 3.10
Classifier: Programming Language :: Python :: 3.11
Classifier: Programming Language :: Python :: 3.12
Requires-Python: >=3.8
License-File: LICENSE
Requires-Dist: lark>=1.1.0
Provides-Extra: dev
Requires-Dist: pytest>=7.0; extra == "dev"
Requires-Dist: pytest-cov>=4.0; extra == "dev"
Requires-Dist: pytest-benchmark>=4.0; extra == "dev"
Requires-Dist: black>=23.0; extra == "dev"
Requires-Dist: flake8>=6.0; extra == "dev"
Requires-Dist: mypy>=1.0; extra == "dev"
Dynamic: license-file
